{
  "name": "CAR IA Photobooth Developer Control Panel 02",
  "description": "/* \u003d\u003d\u003d\u003d\u003d\u003d\u003d\u003d\u003d\u003d\u003d\u003d\u003d\u003d\u003d\u003d\u003d\u003d\u003d\u003d\u003d\u003d\u003d\u003d\u003d\u003d\u003d\u003d\u003d\u003d\u003d\u003d\u003d\u003d\u003d\u003d\u003d\u003d\u003d\u003d\u003d\u003d\u003d\u003d\u003d\u003d\u003d\u003d\u003d\u003d\u003d\u003d\u003d\u003d\u003d\u003d\u003d\u003d\u003d\u003d\u003d\u003d\u003d\u003d\u003d\u003d\u003d\u003d\u003d\u003d\u003d\u003d\u003d\u003d\n   BLUEPRINT TECHNIQUE DE COMPOSITION MATRICIELLE - PWA VERS MOTEUR GENERATION API\n   \u003d\u003d\u003d\u003d\u003d\u003d\u003d\u003d\u003d\u003d\u003d\u003d\u003d\u003d\u003d\u003d\u003d\u003d\u003d\u003d\u003d\u003d\u003d\u003d\u003d\u003d\u003d\u003d\u003d\u003d\u003d\u003d\u003d\u003d\u003d\u003d\u003d\u003d\u003d\u003d\u003d\u003d\u003d\u003d\u003d\u003d\u003d\u003d\u003d\u003d\u003d\u003d\u003d\u003d\u003d\u003d\u003d\u003d\u003d\u003d\u003d\u003d\u003d\u003d\u003d\u003d\u003d\u003d\u003d\u003d\u003d\u003d\u003d\u003d */\n\n1. MISE À JOUR DU PAYLOAD FIRESTORE\n----------------------------------\nLe document Firestore créé dans la collection \"exports\" contient désormais l\u0027objet exact \"boundingBoxVehicule\" de l\u0027image source du véhicule détouré (imageB) sous ce format :\n{\n  \"imageA\": \"URL_image_fond_haute_definition\",\n  \"imageB\": \"URL_image_vehicule_detoure\",\n  \"metadataUtilisateur\": {\n    \"texte\": \"VOTRE TEXTE\",\n    \"transformVehicule\": {\n      \"x\": -2.3,       /* Décalage horizontal en pourcentage par rapport à la Box Virtuelle (960px) */\n      \"y\": 14.5,       /* Décalage vertical en pourcentage par rapport à la Box Virtuelle (960px) */\n      \"scale\": 1.15,   /* Facteur d\u0027échelle additionnel de l\u0027utilisateur */\n      \"rotation\": -1.2 /* Angle de rotation en degrés */\n    },\n    \"boundingBoxVehicule\": {\n      \"left\": 120,     /* Coordonnée X de gauche utile du véhicule dans l\u0027image B d\u0027origine */\n      \"right\": 1480,   /* Coordonnée X de droite utile du véhicule dans l\u0027image B d\u0027origine */\n      \"top\": 210,      /* Coordonnée Y du haut utile du véhicule dans l\u0027image B d\u0027origine */\n      \"bottom\": 780    /* Coordonnée Y du bas utile du véhicule dans l\u0027image B d\u0027origine */\n    }\n  }\n}\n\n2. ALGORITHME DE RECONSTITUTION PIXEL À PIXEL DANS VOTRE API\n-----------------------------------------------------------\nPour reproduire fidèlement l\u0027image finale sur un fond de référence (W_ref x H_ref, ex: 1280 x 1280 px) :\n\nEtape A : Positionnement du conteneur virtuel\n- Un carré virtuel de dimensions Box_Size \u003d 960 px est centré sur le fond de référence (W_ref/2 , H_ref/2).\n\nEtape B : Ratio d\u0027ajustement initial (Object-Contain) du véhicule\nL\u0027image détourée (imageB) d\u0027origine (W_B x H_B) est projetée dans ce carré virtuel de 960x960 px en préservant son ratio d\u0027aspect initial.\n- Si paysage (W_B \u003e H_B) :\n  R_fit \u003d Box_Size / W_B ;\n- Si portrait (W_B \u003c\u003d H_B) :\n  R_fit \u003d Box_Size / H_B ;\n\nEtape C : Calcul de la largeur utile brute (sans échelle additionnelle)\nLa largeur de la zone active/visible du véhicule isolée (les pixels non vides) après son ajustement passif au conteneur est de :\n- L_utile_brute \u003d (right - left) * R_fit ;\n\nEtape D : Calcul de l\u0027échelle d\u0027harmonisation de base vers la cible (900 px)\nPour que la zone active du véhicule fasse par défaut 900 px de large à l\u0027écran (sur la grille de référence de 1280 px) :\n- Echelle_de_base \u003d 900 / L_utile_brute ;\n\nEtape E : Facteur d\u0027échelle total appliqué\nL\u0027échelle finale combinée à appliquer sur le calque du véhicule est :\n- Echelle_Totale \u003d Echelle_de_base * scale ;\n\nEtape F : Coordonnées de l\u0027ancrage de rotation (Centre du véhicule)\nLe centre géométrique sur lequel faire pivoter le calque est décalé depuis le centre absolu du fond de référence (1280 px) :\n- X_ancrage \u003d (W_ref / 2) + (x / 100) * Box_Size ;\n- Y_ancrage \u003d (H_ref / 2) + (y / 100) * Box_Size ;\n\nEtape G : Ordre d\u0027application des transformations\n1. Translation globale vers (X_ancrage, Y_ancrage).\n2. Rotation par rapport à ce point de l\u0027angle \"rotation\" (en degrés).\n3. Dessin du véhicule détouré (imageB) à l\u0027échelle \"Echelle_Totale\" centré sur cette coordonnée d\u0027origine locale :\n   - X_local \u003d - (W_B / 2) * Echelle_Totale ;\n   - Y_local \u003d - (H_B / 2) * Echelle_Totale ;",
  "requestFramePermissions": [],
  "majorCapabilities": [
    "MAJOR_CAPABILITY_SERVER_SIDE_GEMINI_API"
  ]
}